pyfuf/__init__.py
pyfuf/fuzzing.py
pyfuf-0.0.3.dist-info/LICENSE
pyfuf-0.0.3.dist-info/METADATA
pyfuf-0.0.3.dist-info/WHEEL
pyfuf-0.0.3.dist-info/top_level.txt
pyfuf-0.0.3.dist-info/RECORD
