Metadata-Version: 2.1
Name: pyfuf
Version: 0.0.3
Summary: support for fuff in python
Home-page: UNKNOWN
Author: plusleft
License: UNKNOWN
Platform: UNKNOWN
